qfeval_functions/__init__.py
qfeval_functions/version.py
qfeval_functions/functions/__init__.py
qfeval_functions/functions/apply_for_axis.py
qfeval_functions/functions/bfill.py
qfeval_functions/functions/bincount.py
qfeval_functions/functions/bollinger_band.py
qfeval_functions/functions/correl.py
qfeval_functions/functions/covar.py
qfeval_functions/functions/cumcount.py
qfeval_functions/functions/eigh.py
qfeval_functions/functions/einsum.py
qfeval_functions/functions/ema.py
qfeval_functions/functions/ffill.py
qfeval_functions/functions/fillna.py
qfeval_functions/functions/gaussian_blur.py
qfeval_functions/functions/group_shift.py
qfeval_functions/functions/groupby.py
qfeval_functions/functions/ma.py
qfeval_functions/functions/mmax.py
qfeval_functions/functions/mmin.py
qfeval_functions/functions/mstd.py
qfeval_functions/functions/msum.py
qfeval_functions/functions/mulmean.py
qfeval_functions/functions/mulsum.py
qfeval_functions/functions/mvar.py
qfeval_functions/functions/nancorrel.py
qfeval_functions/functions/nancovar.py
qfeval_functions/functions/nancumprod.py
qfeval_functions/functions/nancumsum.py
qfeval_functions/functions/nankurtosis.py
qfeval_functions/functions/nanmax.py
qfeval_functions/functions/nanmean.py
qfeval_functions/functions/nanmin.py
qfeval_functions/functions/nanmulmean.py
qfeval_functions/functions/nanmulsum.py
qfeval_functions/functions/nanones.py
qfeval_functions/functions/nanpca.py
qfeval_functions/functions/nanshift.py
qfeval_functions/functions/nanskew.py
qfeval_functions/functions/nanslope.py
qfeval_functions/functions/nansum.py
qfeval_functions/functions/nanvar.py
qfeval_functions/functions/orthogonalize.py
qfeval_functions/functions/orthonormalize.py
qfeval_functions/functions/pca.py
qfeval_functions/functions/project.py
qfeval_functions/functions/rand.py
qfeval_functions/functions/rand_like.py
qfeval_functions/functions/randint.py
qfeval_functions/functions/randn.py
qfeval_functions/functions/randn_like.py
qfeval_functions-0.1.0.dist-info/licenses/LICENSE
qfeval_functions-0.1.0.dist-info/METADATA
qfeval_functions-0.1.0.dist-info/WHEEL
qfeval_functions-0.1.0.dist-info/top_level.txt
qfeval_functions-0.1.0.dist-info/RECORD
