Metadata-Version: 2.4
Name: qfeval_functions
Version: 0.1.0
Summary: Functions for quantitative finance
Requires-Python: >=3.9
License-File: LICENSE
Requires-Dist: torch
Requires-Dist: numpy
Provides-Extra: cupy
Requires-Dist: cupy; extra == "cupy"
Dynamic: license-file
